preql/__init__.py
preql/compiler.py
preql/constants.py
preql/engine.py
preql/executor.py
preql/parser.py
preql/py.typed
preql/utility.py
preql/core/__init__.py
preql/core/constants.py
preql/core/enums.py
preql/core/env_processor.py
preql/core/environment_helpers.py
preql/core/ergonomics.py
preql/core/exceptions.py
preql/core/functions.py
preql/core/graph_models.py
preql/core/internal.py
preql/core/models.py
preql/core/query_processor.py
preql/core/processing/__init__.py
preql/core/processing/concept_strategies_v3.py
preql/core/processing/graph_utils.py
preql/core/processing/utility.py
preql/core/processing/node_generators/__init__.py
preql/core/processing/node_generators/basic_node.py
preql/core/processing/node_generators/common.py
preql/core/processing/node_generators/concept_merge.py
preql/core/processing/node_generators/filter_node.py
preql/core/processing/node_generators/group_node.py
preql/core/processing/node_generators/group_to_node.py
preql/core/processing/node_generators/merge_node.py
preql/core/processing/node_generators/multiselect_node.py
preql/core/processing/node_generators/rowset_node.py
preql/core/processing/node_generators/select_node.py
preql/core/processing/node_generators/unnest_node.py
preql/core/processing/node_generators/window_node.py
preql/core/processing/nodes/__init__.py
preql/core/processing/nodes/base_node.py
preql/core/processing/nodes/filter_node.py
preql/core/processing/nodes/group_node.py
preql/core/processing/nodes/merge_node.py
preql/core/processing/nodes/select_node_v2.py
preql/core/processing/nodes/unnest_node.py
preql/core/processing/nodes/window_node.py
preql/dialect/__init__.py
preql/dialect/base.py
preql/dialect/bigquery.py
preql/dialect/common.py
preql/dialect/config.py
preql/dialect/duckdb.py
preql/dialect/enums.py
preql/dialect/postgres.py
preql/dialect/presto.py
preql/dialect/snowflake.py
preql/dialect/sql_server.py
preql/docs/__init__.py
preql/hooks/__init__.py
preql/hooks/base_hook.py
preql/hooks/graph_hook.py
pypreql-0.0.1.102.dist-info/LICENSE.md
pypreql-0.0.1.102.dist-info/METADATA
pypreql-0.0.1.102.dist-info/WHEEL
pypreql-0.0.1.102.dist-info/entry_points.txt
pypreql-0.0.1.102.dist-info/top_level.txt
pypreql-0.0.1.102.dist-info/RECORD
