Metadata-Version: 2.1
Name: pypreql
Version: 0.0.1.102
Summary: Declarative, typed query language that compiles to SQL.
Home-page: 
Author: 
Author-email: preql-community@gmail.com
Classifier: Programming Language :: Python
Classifier: Programming Language :: Python :: 3
Classifier: Programming Language :: Python :: 3.9
Classifier: Programming Language :: Python :: 3.10
Classifier: Programming Language :: Python :: 3.11
Classifier: Programming Language :: Python :: 3.12
License-File: LICENSE.md
Requires-Dist: lark
Requires-Dist: jinja2
Requires-Dist: sqlalchemy <2.0.0
Requires-Dist: networkx
Requires-Dist: pyodbc
Requires-Dist: pydantic
Requires-Dist: duckdb-engine
Provides-Extra: bigquery
Requires-Dist: sqlalchemy-bigquery ; extra == 'bigquery'
Provides-Extra: postgres
Requires-Dist: psycopg2-binary ; extra == 'postgres'
Provides-Extra: snowflake
Requires-Dist: snowflake-sqlalchemy ; extra == 'snowflake'
